odoo/addons/account_invoice_pricelist_sale/README.rst
odoo/addons/account_invoice_pricelist_sale/__init__.py
odoo/addons/account_invoice_pricelist_sale/__manifest__.py
odoo/addons/account_invoice_pricelist_sale/i18n/account_invoice_pricelist_sale.pot
odoo/addons/account_invoice_pricelist_sale/i18n/ca.po
odoo/addons/account_invoice_pricelist_sale/i18n/de.po
odoo/addons/account_invoice_pricelist_sale/i18n/el_GR.po
odoo/addons/account_invoice_pricelist_sale/i18n/es.po
odoo/addons/account_invoice_pricelist_sale/i18n/es_ES.po
odoo/addons/account_invoice_pricelist_sale/i18n/es_VE.po
odoo/addons/account_invoice_pricelist_sale/i18n/fi.po
odoo/addons/account_invoice_pricelist_sale/i18n/fr.po
odoo/addons/account_invoice_pricelist_sale/i18n/hr.po
odoo/addons/account_invoice_pricelist_sale/i18n/hr_HR.po
odoo/addons/account_invoice_pricelist_sale/i18n/hu.po
odoo/addons/account_invoice_pricelist_sale/i18n/it.po
odoo/addons/account_invoice_pricelist_sale/i18n/nl.po
odoo/addons/account_invoice_pricelist_sale/i18n/nl_NL.po
odoo/addons/account_invoice_pricelist_sale/i18n/pt.po
odoo/addons/account_invoice_pricelist_sale/i18n/pt_BR.po
odoo/addons/account_invoice_pricelist_sale/i18n/ro.po
odoo/addons/account_invoice_pricelist_sale/i18n/sl.po
odoo/addons/account_invoice_pricelist_sale/i18n/tr.po
odoo/addons/account_invoice_pricelist_sale/i18n/tr_TR.po
odoo/addons/account_invoice_pricelist_sale/i18n/vi_VN.po
odoo/addons/account_invoice_pricelist_sale/i18n/zh_CN.po
odoo/addons/account_invoice_pricelist_sale/models/__init__.py
odoo/addons/account_invoice_pricelist_sale/models/sale_order.py
odoo/addons/account_invoice_pricelist_sale/readme/CONTRIBUTORS.rst
odoo/addons/account_invoice_pricelist_sale/readme/DESCRIPTION.rst
odoo/addons/account_invoice_pricelist_sale/readme/INSTALLATION.rst
odoo/addons/account_invoice_pricelist_sale/static/description/icon.png
odoo/addons/account_invoice_pricelist_sale/static/description/index.html
odoo/addons/account_invoice_pricelist_sale/tests/__init__.py
odoo12_addon_account_invoice_pricelist_sale-12.0.1.0.0.99.dev12.dist-info/METADATA
odoo12_addon_account_invoice_pricelist_sale-12.0.1.0.0.99.dev12.dist-info/WHEEL
odoo12_addon_account_invoice_pricelist_sale-12.0.1.0.0.99.dev12.dist-info/top_level.txt
odoo12_addon_account_invoice_pricelist_sale-12.0.1.0.0.99.dev12.dist-info/RECORD
